board_game_merger/__init__.py
board_game_merger/__main__.py
board_game_merger/config.py
board_game_merger/merge.py
board_game_merger/py.typed
board_game_merger/schemas.py
board_game_merger-1.0.0.dist-info/LICENSE
board_game_merger-1.0.0.dist-info/METADATA
board_game_merger-1.0.0.dist-info/WHEEL
board_game_merger-1.0.0.dist-info/RECORD
