Metadata-Version: 2.1
Name: board-game-merger
Version: 1.0.0
Summary: Merging board game data
Home-page: https://MarkusShepherd.github.io/board-game-merger
License: MIT
Author: Markus Shepherd
Author-email: markus@recommend.games
Requires-Python: >=3.9.0,<4.0
Classifier: Development Status :: 4 - Beta
Classifier: Intended Audience :: Developers
Classifier: License :: OSI Approved :: MIT License
Classifier: Operating System :: OS Independent
Classifier: Programming Language :: Python
Classifier: Programming Language :: Python :: 3
Classifier: Programming Language :: Python :: 3.9
Classifier: Programming Language :: Python :: 3.10
Classifier: Programming Language :: Python :: 3.11
Classifier: Programming Language :: Python :: 3.12
Classifier: Programming Language :: Python :: 3.13
Classifier: Topic :: Software Development :: Libraries :: Python Modules
Classifier: Typing :: Typed
Requires-Dist: polars (>=1.0.0,<2.0.0)
Requires-Dist: tqdm
Project-URL: Documentation, https://MarkusShepherd.github.io/board-game-merger
Project-URL: Repository, https://github.com/MarkusShepherd/board-game-merger
